{
  "label": "p5_10_ty_schoen_5sigma_n20",
  "path_label": "Path A: n_pts boost",
  "n_pts": 25000,
  "seeds": [
    42,
    100,
    12345,
    7,
    99,
    1,
    2,
    3,
    4,
    5,
    137,
    271,
    314,
    666,
    1000,
    2024,
    4242,
    57005,
    48879,
    51966
  ],
  "donaldson_iters": 50,
  "donaldson_tol": 1e-6,
  "boot_resamples": 1000,
  "boot_seed": 12345,
  "candidates": [
    {
      "candidate": "TY",
      "k": 3,
      "n_pts": 25000,
      "seeds": [
        42,
        100,
        12345,
        7,
        99,
        1,
        2,
        3,
        4,
        5,
        137,
        271,
        314,
        666,
        1000,
        2024,
        4242,
        57005,
        48879,
        51966
      ],
      "per_seed": [
        {
          "seed": 42,
          "candidate": "TY",
          "k": 3,
          "elapsed_s": 10.9865837,
          "n_basis": 87,
          "iterations_run": 17,
          "sigma_final": 0.27158734141107926,
          "sigma_fs_identity": 0.4142606630232887,
          "final_donaldson_residual": 5.175001891011667e-7,
          "convergence_tier": "converged"
        },
        {
          "seed": 100,
          "candidate": "TY",
          "k": 3,
          "elapsed_s": 9.6418854,
          "n_basis": 87,
          "iterations_run": 15,
          "sigma_final": 0.25958465617666426,
          "sigma_fs_identity": 0.4149015526098159,
          "final_donaldson_residual": 6.57368645371876e-7,
          "convergence_tier": "converged"
        },
        {
          "seed": 12345,
          "candidate": "TY",
          "k": 3,
          "elapsed_s": 10.1999553,
          "n_basis": 87,
          "iterations_run": 16,
          "sigma_final": 0.2716856238752092,
          "sigma_fs_identity": 0.4189832969092631,
          "final_donaldson_residual": 6.355370515484334e-7,
          "convergence_tier": "converged"
        },
        {
          "seed": 7,
          "candidate": "TY",
          "k": 3,
          "elapsed_s": 10.9515364,
          "n_basis": 87,
          "iterations_run": 17,
          "sigma_final": 0.27356962215301833,
          "sigma_fs_identity": 0.41947385719827696,
          "final_donaldson_residual": 7.886657014003708e-7,
          "convergence_tier": "converged"
        },
        {
          "seed": 99,
          "candidate": "TY",
          "k": 3,
          "elapsed_s": 11.3290839,
          "n_basis": 87,
          "iterations_run": 17,
          "sigma_final": 0.264451380753719,
          "sigma_fs_identity": 0.407552726335998,
          "final_donaldson_residual": 6.006946312241025e-7,
          "convergence_tier": "converged"
        },
        {
          "seed": 1,
          "candidate": "TY",
          "k": 3,
          "elapsed_s": 11.53717,
          "n_basis": 87,
          "iterations_run": 17,
          "sigma_final": 0.2653893086712421,
          "sigma_fs_identity": 0.40321088375130637,
          "final_donaldson_residual": 8.754754654493274e-7,
          "convergence_tier": "converged"
        },
        {
          "seed": 2,
          "candidate": "TY",
          "k": 3,
          "elapsed_s": 11.1870296,
          "n_basis": 87,
          "iterations_run": 17,
          "sigma_final": 0.26897154858274186,
          "sigma_fs_identity": 0.3990431716472298,
          "final_donaldson_residual": 7.69723823071615e-7,
          "convergence_tier": "converged"
        },
        {
          "seed": 3,
          "candidate": "TY",
          "k": 3,
          "elapsed_s": 11.4302683,
          "n_basis": 87,
          "iterations_run": 17,
          "sigma_final": 0.2668496601039738,
          "sigma_fs_identity": 0.4060790262595383,
          "final_donaldson_residual": 5.609654484134103e-7,
          "convergence_tier": "converged"
        },
        {
          "seed": 4,
          "candidate": "TY",
          "k": 3,
          "elapsed_s": 11.6618119,
          "n_basis": 87,
          "iterations_run": 17,
          "sigma_final": 0.26364464861303677,
          "sigma_fs_identity": 0.4041286729005112,
          "final_donaldson_residual": 7.491463740238768e-7,
          "convergence_tier": "converged"
        },
        {
          "seed": 5,
          "candidate": "TY",
          "k": 3,
          "elapsed_s": 10.406907499999999,
          "n_basis": 87,
          "iterations_run": 16,
          "sigma_final": 0.2717400929228904,
          "sigma_fs_identity": 0.42731950244088474,
          "final_donaldson_residual": 6.073157473189406e-7,
          "convergence_tier": "converged"
        },
        {
          "seed": 137,
          "candidate": "TY",
          "k": 3,
          "elapsed_s": 12.045617,
          "n_basis": 87,
          "iterations_run": 18,
          "sigma_final": 0.26897323888621577,
          "sigma_fs_identity": 0.4121095308835192,
          "final_donaldson_residual": 5.039378084479347e-7,
          "convergence_tier": "converged"
        },
        {
          "seed": 271,
          "candidate": "TY",
          "k": 3,
          "elapsed_s": 12.1785756,
          "n_basis": 87,
          "iterations_run": 18,
          "sigma_final": 0.2655922627150386,
          "sigma_fs_identity": 0.40563231318479476,
          "final_donaldson_residual": 6.795434034122358e-7,
          "convergence_tier": "converged"
        },
        {
          "seed": 314,
          "candidate": "TY",
          "k": 3,
          "elapsed_s": 11.8556336,
          "n_basis": 87,
          "iterations_run": 18,
          "sigma_final": 0.2748640890309448,
          "sigma_fs_identity": 0.41195539749234256,
          "final_donaldson_residual": 6.102592594455927e-7,
          "convergence_tier": "converged"
        },
        {
          "seed": 666,
          "candidate": "TY",
          "k": 3,
          "elapsed_s": 11.9044244,
          "n_basis": 87,
          "iterations_run": 18,
          "sigma_final": 0.27248372069039417,
          "sigma_fs_identity": 0.41981658459824867,
          "final_donaldson_residual": 6.686671827829312e-7,
          "convergence_tier": "converged"
        },
        {
          "seed": 1000,
          "candidate": "TY",
          "k": 3,
          "elapsed_s": 11.6579883,
          "n_basis": 87,
          "iterations_run": 18,
          "sigma_final": 0.2683046655125121,
          "sigma_fs_identity": 0.40928638552475527,
          "final_donaldson_residual": 6.101214639552767e-7,
          "convergence_tier": "converged"
        },
        {
          "seed": 2024,
          "candidate": "TY",
          "k": 3,
          "elapsed_s": 11.0010761,
          "n_basis": 87,
          "iterations_run": 17,
          "sigma_final": 0.26672664267080726,
          "sigma_fs_identity": 0.4087175288511491,
          "final_donaldson_residual": 8.018236813862719e-7,
          "convergence_tier": "converged"
        },
        {
          "seed": 4242,
          "candidate": "TY",
          "k": 3,
          "elapsed_s": 10.557045800000001,
          "n_basis": 87,
          "iterations_run": 16,
          "sigma_final": 0.26489556010037985,
          "sigma_fs_identity": 0.404097805695144,
          "final_donaldson_residual": 5.423195216274127e-7,
          "convergence_tier": "converged"
        },
        {
          "seed": 57005,
          "candidate": "TY",
          "k": 3,
          "elapsed_s": 11.6250598,
          "n_basis": 87,
          "iterations_run": 18,
          "sigma_final": 0.26738801521297745,
          "sigma_fs_identity": 0.4074605163430491,
          "final_donaldson_residual": 5.652977151855935e-7,
          "convergence_tier": "converged"
        },
        {
          "seed": 48879,
          "candidate": "TY",
          "k": 3,
          "elapsed_s": 11.1975907,
          "n_basis": 87,
          "iterations_run": 17,
          "sigma_final": 0.265635672839122,
          "sigma_fs_identity": 0.40655853076838694,
          "final_donaldson_residual": 5.825154991765662e-7,
          "convergence_tier": "converged"
        },
        {
          "seed": 51966,
          "candidate": "TY",
          "k": 3,
          "elapsed_s": 11.7670603,
          "n_basis": 87,
          "iterations_run": 18,
          "sigma_final": 0.27383660450080044,
          "sigma_fs_identity": 0.41567314961113416,
          "final_donaldson_residual": 5.730132239258214e-7,
          "convergence_tier": "converged"
        }
      ],
      "sigma_stats": {
        "name": "sigma_ty_k3",
        "n": 20,
        "mean": 0.2683087177711384,
        "std": 0.004015526299902652,
        "stderr": 0.0008978989772020537,
        "percentile_ci_low": 0.2666510369913452,
        "percentile_ci_high": 0.2700187577610627,
        "bca_ci_low": 0.2666012947818,
        "bca_ci_high": 0.2699016403871063
      }
    },
    {
      "candidate": "Schoen",
      "k": 3,
      "n_pts": 25000,
      "seeds": [
        42,
        100,
        12345,
        7,
        99,
        1,
        2,
        3,
        4,
        5,
        137,
        271,
        314,
        666,
        1000,
        2024,
        4242,
        57005,
        48879,
        51966
      ],
      "per_seed": [
        {
          "seed": 42,
          "candidate": "Schoen",
          "k": 3,
          "elapsed_s": 1.9471140999999998,
          "n_basis": 27,
          "iterations_run": 22,
          "sigma_final": 2.3512591541809718,
          "sigma_fs_identity": 1.7383388687114818,
          "final_donaldson_residual": 7.516914706631116e-7,
          "convergence_tier": "converged"
        },
        {
          "seed": 100,
          "candidate": "Schoen",
          "k": 3,
          "elapsed_s": 1.7051692,
          "n_basis": 27,
          "iterations_run": 19,
          "sigma_final": 1.6429143159188024,
          "sigma_fs_identity": 1.466815634988972,
          "final_donaldson_residual": 7.04259940684085e-7,
          "convergence_tier": "converged"
        },
        {
          "seed": 12345,
          "candidate": "Schoen",
          "k": 3,
          "elapsed_s": 2.0971602,
          "n_basis": 27,
          "iterations_run": 24,
          "sigma_final": 1.8522547541722887,
          "sigma_fs_identity": 1.5125202687750847,
          "final_donaldson_residual": 7.54644076245682e-7,
          "convergence_tier": "converged"
        },
        {
          "seed": 7,
          "candidate": "Schoen",
          "k": 3,
          "elapsed_s": 3.3675118,
          "n_basis": 27,
          "iterations_run": 40,
          "sigma_final": 4.014757293360359,
          "sigma_fs_identity": 1.855369927366961,
          "final_donaldson_residual": 9.286504982517146e-7,
          "convergence_tier": "converged"
        },
        {
          "seed": 99,
          "candidate": "Schoen",
          "k": 3,
          "elapsed_s": 4.2511449,
          "n_basis": 27,
          "iterations_run": 50,
          "sigma_final": 6.269586450382732,
          "sigma_fs_identity": 2.2869703919655593,
          "final_donaldson_residual": 2.389272978028687e-6,
          "convergence_tier": "converged"
        },
        {
          "seed": 1,
          "candidate": "Schoen",
          "k": 3,
          "elapsed_s": 2.2035955,
          "n_basis": 27,
          "iterations_run": 25,
          "sigma_final": 4.283196594488561,
          "sigma_fs_identity": 2.4211849312031233,
          "final_donaldson_residual": 8.061196702260121e-7,
          "convergence_tier": "converged"
        },
        {
          "seed": 2,
          "candidate": "Schoen",
          "k": 3,
          "elapsed_s": 0.483095,
          "n_basis": 27,
          "iterations_run": 3,
          "sigma_final": 5.266518883116879,
          "sigma_fs_identity": 2.056472828905858,
          "final_donaldson_residual": 0.08763437868799322,
          "convergence_tier": "non-converged"
        },
        {
          "seed": 3,
          "candidate": "Schoen",
          "k": 3,
          "elapsed_s": 3.6833715,
          "n_basis": 27,
          "iterations_run": 43,
          "sigma_final": 2.8917621518217653,
          "sigma_fs_identity": 1.6819881784224393,
          "final_donaldson_residual": 9.257824756265942e-7,
          "convergence_tier": "converged"
        },
        {
          "seed": 4,
          "candidate": "Schoen",
          "k": 3,
          "elapsed_s": 2.0889346,
          "n_basis": 27,
          "iterations_run": 24,
          "sigma_final": 5.9507196728762795,
          "sigma_fs_identity": 1.7503320389357409,
          "final_donaldson_residual": 7.845479720777224e-7,
          "convergence_tier": "converged"
        },
        {
          "seed": 5,
          "candidate": "Schoen",
          "k": 3,
          "elapsed_s": 0.442542,
          "n_basis": 27,
          "iterations_run": 2,
          "sigma_final": 6.780186058210525,
          "sigma_fs_identity": 2.7815541118663147,
          "final_donaldson_residual": 0.4854022284375044,
          "convergence_tier": "non-converged"
        },
        {
          "seed": 137,
          "candidate": "Schoen",
          "k": 3,
          "elapsed_s": 4.1885728,
          "n_basis": 27,
          "iterations_run": 50,
          "sigma_final": 3.6349038122049824,
          "sigma_fs_identity": 1.5453104660234542,
          "final_donaldson_residual": 8.509452669478076e-7,
          "convergence_tier": "converged"
        },
        {
          "seed": 271,
          "candidate": "Schoen",
          "k": 3,
          "elapsed_s": 0.5610416,
          "n_basis": 27,
          "iterations_run": 4,
          "sigma_final": 4.666330495512352,
          "sigma_fs_identity": 2.066352578124536,
          "final_donaldson_residual": 0.1527861121600454,
          "convergence_tier": "non-converged"
        },
        {
          "seed": 314,
          "candidate": "Schoen",
          "k": 3,
          "elapsed_s": 2.4489729000000002,
          "n_basis": 27,
          "iterations_run": 28,
          "sigma_final": 3.3115652123042483,
          "sigma_fs_identity": 2.249931487681903,
          "final_donaldson_residual": 6.855120420950215e-7,
          "convergence_tier": "converged"
        },
        {
          "seed": 666,
          "candidate": "Schoen",
          "k": 3,
          "elapsed_s": 3.9147437,
          "n_basis": 27,
          "iterations_run": 46,
          "sigma_final": 12.30861622429355,
          "sigma_fs_identity": 7.429190974064944,
          "final_donaldson_residual": 9.11581836849299e-7,
          "convergence_tier": "converged"
        },
        {
          "seed": 1000,
          "candidate": "Schoen",
          "k": 3,
          "elapsed_s": 0.6645242,
          "n_basis": 27,
          "iterations_run": 5,
          "sigma_final": 15.530037546899662,
          "sigma_fs_identity": 2.246513828215183,
          "final_donaldson_residual": 0.05452231421841497,
          "convergence_tier": "non-converged"
        },
        {
          "seed": 2024,
          "candidate": "Schoen",
          "k": 3,
          "elapsed_s": 0.9436845,
          "n_basis": 27,
          "iterations_run": 9,
          "sigma_final": 3.6635979003103074,
          "sigma_fs_identity": 1.6611457689625029,
          "final_donaldson_residual": 0.00449645897234078,
          "convergence_tier": "ambiguous"
        },
        {
          "seed": 4242,
          "candidate": "Schoen",
          "k": 3,
          "elapsed_s": 3.5878259,
          "n_basis": 27,
          "iterations_run": 42,
          "sigma_final": 4.851141232402019,
          "sigma_fs_identity": 4.5167931194499,
          "final_donaldson_residual": 8.009746618671698e-7,
          "convergence_tier": "converged"
        },
        {
          "seed": 57005,
          "candidate": "Schoen",
          "k": 3,
          "elapsed_s": 0.6001931,
          "n_basis": 27,
          "iterations_run": 4,
          "sigma_final": 9.263221670135756,
          "sigma_fs_identity": 2.018786108071891,
          "final_donaldson_residual": 0.10502175434379742,
          "convergence_tier": "non-converged"
        },
        {
          "seed": 48879,
          "candidate": "Schoen",
          "k": 3,
          "elapsed_s": 1.9774973,
          "n_basis": 27,
          "iterations_run": 22,
          "sigma_final": 2.377675271322811,
          "sigma_fs_identity": 1.844559716205459,
          "final_donaldson_residual": 6.534995280719386e-7,
          "convergence_tier": "converged"
        },
        {
          "seed": 51966,
          "candidate": "Schoen",
          "k": 3,
          "elapsed_s": 1.6495923000000001,
          "n_basis": 27,
          "iterations_run": 18,
          "sigma_final": 6.456219527626889,
          "sigma_fs_identity": 4.874896141447248,
          "final_donaldson_residual": 9.342581390689197e-7,
          "convergence_tier": "converged"
        }
      ],
      "sigma_stats": {
        "name": "sigma_schoen_k3",
        "n": 20,
        "mean": 5.3683232110770875,
        "std": 3.5188922440171964,
        "stderr": 0.7868482263119229,
        "percentile_ci_low": 4.056109162655345,
        "percentile_ci_high": 6.9525362779345,
        "bca_ci_low": 4.1745674740299,
        "bca_ci_high": 7.189127748745227
      }
    }
  ],
  "discrimination": [
    {
      "k": 3,
      "mean_ty": 0.2683087177711384,
      "se_ty": 0.0008978989772020537,
      "n_ty": 20,
      "mean_schoen": 5.3683232110770875,
      "se_schoen": 0.7868482263119229,
      "n_schoen": 20,
      "delta_sigma": -5.100014493305949,
      "se_combined": 0.7868487386231182,
      "n_sigma": 6.481569128814139,
      "n_sigma_ci_low": 5.320184585200775,
      "n_sigma_ci_high": 10.881989692225604,
      "n_sigma_boot_resamples": 1000,
      "subset_label": "conservative"
    }
  ],
  "discrimination_balanced_only": [
    {
      "k": 3,
      "mean_ty": 0.2683087177711384,
      "se_ty": 0.0008978989772020537,
      "n_ty": 20,
      "mean_schoen": 4.442612261954018,
      "se_schoen": 0.7391672028615885,
      "n_schoen": 14,
      "delta_sigma": -4.174303544182879,
      "se_combined": 0.7391677482201169,
      "n_sigma": 5.647302055906006,
      "n_sigma_ci_low": 4.423354376918716,
      "n_sigma_ci_high": 11.039445126094444,
      "n_sigma_boot_resamples": 1000,
      "subset_label": "balanced_only_iters_ge_10"
    }
  ],
  "discrimination_canonical": [
    {
      "k": 3,
      "mean_ty": 0.2683087177711384,
      "se_ty": 0.0008978989772020537,
      "n_ty": 20,
      "mean_schoen": 4.442612261954018,
      "se_schoen": 0.7391672028615885,
      "n_schoen": 14,
      "delta_sigma": -4.174303544182879,
      "se_combined": 0.7391677482201169,
      "n_sigma": 5.647302055906006,
      "n_sigma_ci_low": 4.423354376918716,
      "n_sigma_ci_high": 11.039445126094444,
      "n_sigma_boot_resamples": 1000,
      "subset_label": "canonical"
    }
  ],
  "discrimination_reference": [
    {
      "k": 3,
      "mean_ty": 0.2683087177711384,
      "se_ty": 0.0008978989772020537,
      "n_ty": 20,
      "mean_schoen": 3.8375350340817467,
      "se_schoen": 0.45857531454793465,
      "n_schoen": 13,
      "delta_sigma": -3.5692263163106084,
      "se_combined": 0.4585761935985235,
      "n_sigma": 7.783278692036535,
      "n_sigma_ci_low": 6.184610150983147,
      "n_sigma_ci_high": 11.55252721915506,
      "n_sigma_boot_resamples": 1000,
      "subset_label": "reference"
    }
  ],
  "early_bail_seeds": [
    {
      "seed": 2,
      "candidate": "Schoen",
      "iterations_run": 3,
      "sigma_final": 5.266518883116879,
      "sigma_fs_identity": 2.056472828905858,
      "rel_diff_to_fs": 1.5609474674746464
    },
    {
      "seed": 5,
      "candidate": "Schoen",
      "iterations_run": 2,
      "sigma_final": 6.780186058210525,
      "sigma_fs_identity": 2.7815541118663147,
      "rel_diff_to_fs": 1.4375531755020519
    },
    {
      "seed": 271,
      "candidate": "Schoen",
      "iterations_run": 4,
      "sigma_final": 4.666330495512352,
      "sigma_fs_identity": 2.066352578124536,
      "rel_diff_to_fs": 1.258245056972615
    },
    {
      "seed": 1000,
      "candidate": "Schoen",
      "iterations_run": 5,
      "sigma_final": 15.530037546899662,
      "sigma_fs_identity": 2.246513828215183,
      "rel_diff_to_fs": 5.912949901242323
    },
    {
      "seed": 2024,
      "candidate": "Schoen",
      "iterations_run": 9,
      "sigma_final": 3.6635979003103074,
      "sigma_fs_identity": 1.6611457689625029,
      "rel_diff_to_fs": 1.2054644262787788
    },
    {
      "seed": 57005,
      "candidate": "Schoen",
      "iterations_run": 4,
      "sigma_final": 9.263221670135756,
      "sigma_fs_identity": 2.018786108071891,
      "rel_diff_to_fs": 3.5885107060613297
    }
  ],
  "balanced_min_iters": 10,
  "converged_residual_threshold": 0.001,
  "ambiguous_residual_threshold": 0.01,
  "max_n_sigma": 6.481569128814139,
  "max_n_sigma_k": 3,
  "five_sigma_achieved": true,
  "total_elapsed_s": 267.9400025,
  "git_revision": "a90ced977d60db8224419f66f89e98789bd979a4"
}