{
  "label": "p_stage3_g1_basis_sweep",
  "settings": {
    "n_pts": 300,
    "k": 2,
    "iter_cap": 3,
    "donaldson_tol": 0.1,
    "seed": 12345,
    "degrees": [
      1
    ]
  },
  "per_candidate": [
    {
      "label": "TY/Z3",
      "geometry": "TianYau bicubic CP^3 x CP^3, Z/3 quotient",
      "bundle": "AKLP (Anderson-Lukas-Palti) SU(5) monad bundle, single-Z/3 Wilson line",
      "per_degree": [
        {
          "completion_degree": 1,
          "status": "OK",
          "lepton_masses_mev": [
            0.0,
            0.0,
            0.0
          ],
          "up_quark_masses_mev": [
            0.0,
            0.0,
            135976.02723958087
          ],
          "down_quark_masses_mev": [
            0.0,
            0.0,
            0.0
          ],
          "eigenvalue_ratios": [
            0.0,
            0.0,
            0.0,
            0.0,
            0.0,
            0.0
          ],
          "cohomology_dim_observed": 9,
          "cohomology_dim_predicted": 9,
          "used_kernel_dim_fallback": false,
          "quadrature_uniformity_score": 0.632800357154867,
          "convergence_ratio": 0.513489437238306,
          "harmonic_orthonormality_residual": 2.4156803899964174e-9,
          "elapsed_s": 0.0040804
        }
      ],
      "verdict": "FIX_A_INSUFFICIENT: rank-1 collapse persists at all swept caps"
    },
    {
      "label": "Schoen/Z3xZ3",
      "geometry": "Schoen CP^2 x CP^2 x CP^1, (d_x,d_y,d_t)=(2,2,1), Z/3 x Z/3 quotient",
      "bundle": "Schoen Z/3 x Z/3 canonical monad bundle, WilsonLineE8 quotient_order=9",
      "per_degree": [
        {
          "completion_degree": 1,
          "status": "OK",
          "lepton_masses_mev": [
            0.0,
            0.0,
            0.0
          ],
          "up_quark_masses_mev": [
            0.0,
            0.0,
            1.081787897119609
          ],
          "down_quark_masses_mev": [
            0.0,
            0.0,
            0.0
          ],
          "eigenvalue_ratios": [
            0.0,
            0.0,
            0.0,
            0.0,
            0.0,
            0.0
          ],
          "cohomology_dim_observed": 2,
          "cohomology_dim_predicted": 0,
          "used_kernel_dim_fallback": false,
          "quadrature_uniformity_score": 0.21926715859063597,
          "convergence_ratio": 0.10019723904791959,
          "harmonic_orthonormality_residual": 1.1051053663732656e-13,
          "elapsed_s": 0.0018592
        }
      ],
      "verdict": "FIX_A_INSUFFICIENT: rank-1 collapse persists at all swept caps"
    }
  ],
  "decision": "FIX_A_INSUFFICIENT",
  "recommended_completion_degree": null,
  "total_elapsed_s": 0.0626335,
  "git_revision": "413a90e41d4fd61f0fcabff8ed82f943fc971879"
}